LICENSE
README.md
setup.cfg
setup.py
ghfetch/__init__.py
ghfetch/main.py
ghfetch/data/__init__.py
ghfetch/data/language-colors.json
ghfetch_pip.egg-info/PKG-INFO
ghfetch_pip.egg-info/SOURCES.txt
ghfetch_pip.egg-info/dependency_links.txt
ghfetch_pip.egg-info/entry_points.txt
ghfetch_pip.egg-info/requires.txt
ghfetch_pip.egg-info/top_level.txt