Metadata-Version: 2.1
Name: ghfetch-pip
Version: 1.9.1
Summary: CLI tool to fetch GitHub information
Home-page: https://github.com/ghfetch/ghfetch
Author: Nullgaro, Icutum
Author-email: ghfetch.contact@gmail.com
License-File: LICENSE
